<?xml version="1.0" encoding="UTF-8" standalone="no"?><soapenv:Envelope xmlns:q0="http://www.comverse.com" xmlns:soapenv="http://schemas.xmlsoap.org/soap/envelope/" xmlns:xsd="http://www.w3.org/2001/XMLSchema" xmlns:xsi="http://www.w3.org/2001/XMLSchema-instance"><soapenv:Body xmlns:xs="http://www.w3.org/2001/XMLSchema"> 
<q0:SubscriberAddOfferInstanceResponse xsi:schemaLocation="http://www.w3.org/2001/XMLSchema" xmlns:q0="http://www.comverse.com" xmlns:xsi="http://www.w3.org/2001/XMLSchema-instance"><q0:output><productVersion>CCBS3.0</productVersion><ServerIdLocator><billingServerId>43</billingServerId><ratingServerId>9</ratingServerId></ServerIdLocator><elapsedTime>10</elapsedTime><serverDate>2020-04-24T14:44:12.257+02:00</serverDate><totalCount>1</totalCount><output><offerInstanceList><attribs>1</attribs><viewId changed="true" set="true"><value>51418615043</value></viewId><offerInstId changed="true" set="true"><value>22477557043</value></offerInstId><accountInternalId changed="true" set="true"><value>0</value></accountInternalId><activeDt changed="true" set="true"><value>2020-04-24T14:44:11.711+02:00</value></activeDt><agentId changed="true" set="true"><value xsi:nil="true"/></agentId><bonusCheckDate xsi:nil="true"/><bundleId xsi:nil="true"/><bundleInstId xsi:nil="true"/><campaignTargetInstId xsi:nil="true"/><chgDt changed="true" set="true"><value>2020-04-24T14:44:11.898+02:00</value></chgDt><chgWho changed="true" set="true"><value>bulkprov</value></chgWho><connectReason changed="true" set="true"><value>1</value></connectReason><contractId xsi:nil="true"/><contractTakeoverCount xsi:nil="true"/><dealerId changed="true" set="true"><value xsi:nil="true"/></dealerId><disconnectReason xsi:nil="true"/><extendedData changed="true" set="true"><value>&lt;ExtendedData&gt;&lt;Parameter name="annotation"&gt;&lt;StringValue&gt;0&lt;/StringValue&gt;&lt;/Parameter&gt;&lt;Parameter name="Fluency"&gt;&lt;IntegerValue&gt;1&lt;/IntegerValue&gt;&lt;/Parameter&gt;&lt;Parameter name="SYSPRO_INVENTORY_COUNT"&gt;&lt;IntegerValue&gt;1&lt;/IntegerValue&gt;&lt;/Parameter&gt;&lt;/ExtendedData&gt;</value></extendedData><externalAgreementId changed="true" set="true"><value>6739</value></externalAgreementId><guidedAccountNo changed="true" set="true"><value>4841245</value></guidedAccountNo><inUse changed="true" set="true"><value>1</value></inUse><inactiveDt changed="true" set="true"><value>2020-10-24T14:44:11.711+02:00</value></inactiveDt><initialContractStartDt xsi:nil="true"/><intendedViewEffectiveDt changed="true" set="true"><value>2020-04-24T14:44:11.771+02:00</value></intendedViewEffectiveDt><latestInstDate changed="true" set="true"><value>2020-04-24T14:44:11.898+02:00</value></latestInstDate><offerId changed="true" set="true"><value>6739</value></offerId><offerState changed="true" set="true"><value>1</value></offerState><offerType changed="true" set="true"><value>3</value></offerType><parentAccountInternalId changed="true" set="true"><value>4841245</value></parentAccountInternalId><paymentMode changed="true" set="true"><value>5</value></paymentMode><prevInactiveDt xsi:nil="true"/><prevViewId xsi:nil="true"/><qualifiedAwardsCounter xsi:nil="true"/><rpoAwardCntr changed="true" set="true"><value>0</value></rpoAwardCntr><rpoState xsi:nil="true"/><selectionType xsi:nil="true"/><serviceInternalId changed="true" set="true"><value>2861244</value></serviceInternalId><serviceInternalIdResets changed="true" set="true"><value>0</value></serviceInternalIdResets><viewCreatedDt changed="true" set="true"><value>2020-04-24T14:44:11.771+02:00</value></viewCreatedDt><viewEffectiveDt changed="true" set="true"><value>2020-04-24T14:44:11.771+02:00</value></viewEffectiveDt><viewStatus changed="true" set="true"><value>1</value></viewStatus><waiveActivation changed="true" set="true"><value>false</value></waiveActivation><waiveTermination changed="true" set="true"><value>false</value></waiveTermination><waiveUnmetCommitment changed="true" set="true"><value>false</value></waiveUnmetCommitment><isRpoActiveNotifSent changed="true" set="true"><value>false</value></isRpoActiveNotifSent><externalId xsi:nil="true"/></offerInstanceList><offerInstanceList><attribs>1</attribs><viewId changed="true" set="true"><value>51418616043</value></viewId><offerInstId changed="true" set="true"><value>22477558043</value></offerInstId><accountInternalId changed="true" set="true"><value>0</value></accountInternalId><activeDt changed="true" set="true"><value>2020-04-24T14:44:11.711+02:00</value></activeDt><agentId changed="true" set="true"><value xsi:nil="true"/></agentId><bonusCheckDate xsi:nil="true"/><bundleId xsi:nil="true"/><bundleInstId xsi:nil="true"/><campaignTargetInstId xsi:nil="true"/><chgDt changed="true" set="true"><value>2020-04-24T14:44:11.930+02:00</value></chgDt><chgWho changed="true" set="true"><value>bulkprov</value></chgWho><connectReason changed="true" set="true"><value>1</value></connectReason><contractId xsi:nil="true"/><contractTakeoverCount xsi:nil="true"/><dealerId changed="true" set="true"><value xsi:nil="true"/></dealerId><disconnectReason xsi:nil="true"/><extendedData changed="true" set="true"><value>&lt;ExtendedData&gt;&lt;Parameter name="annotation"&gt;&lt;StringValue&gt;0&lt;/StringValue&gt;&lt;/Parameter&gt;&lt;Parameter name="Fluency"&gt;&lt;IntegerValue&gt;1&lt;/IntegerValue&gt;&lt;/Parameter&gt;&lt;Parameter name="SYSPRO_INVENTORY_COUNT"&gt;&lt;IntegerValue&gt;1&lt;/IntegerValue&gt;&lt;/Parameter&gt;&lt;/ExtendedData&gt;</value></extendedData><externalAgreementId changed="true" set="true"><value>6738</value></externalAgreementId><guidedAccountNo changed="true" set="true"><value>4841245</value></guidedAccountNo><inUse changed="true" set="true"><value>1</value></inUse><inactiveDt changed="true" set="true"><value>2020-10-24T14:44:11.711+02:00</value></inactiveDt><initialContractStartDt xsi:nil="true"/><intendedViewEffectiveDt changed="true" set="true"><value>2020-04-24T14:44:11.777+02:00</value></intendedViewEffectiveDt><latestInstDate changed="true" set="true"><value>2020-04-24T14:44:11.931+02:00</value></latestInstDate><offerId changed="true" set="true"><value>6738</value></offerId><offerState changed="true" set="true"><value>2</value></offerState><offerType changed="true" set="true"><value>3</value></offerType><parentAccountInternalId changed="true" set="true"><value>4841245</value></parentAccountInternalId><paymentMode changed="true" set="true"><value>5</value></paymentMode><prevInactiveDt xsi:nil="true"/><prevViewId xsi:nil="true"/><qualifiedAwardsCounter xsi:nil="true"/><rpoAwardCntr changed="true" set="true"><value>0</value></rpoAwardCntr><rpoState xsi:nil="true"/><selectionType xsi:nil="true"/><serviceInternalId changed="true" set="true"><value>2861244</value></serviceInternalId><serviceInternalIdResets changed="true" set="true"><value>0</value></serviceInternalIdResets><viewCreatedDt changed="true" set="true"><value>2020-04-24T14:44:11.777+02:00</value></viewCreatedDt><viewEffectiveDt changed="true" set="true"><value>2020-04-24T14:44:11.777+02:00</value></viewEffectiveDt><viewStatus changed="true" set="true"><value>1</value></viewStatus><waiveActivation changed="true" set="true"><value>false</value></waiveActivation><waiveTermination changed="true" set="true"><value>false</value></waiveTermination><waiveUnmetCommitment changed="true" set="true"><value>false</value></waiveUnmetCommitment><isRpoActiveNotifSent changed="true" set="true"><value>false</value></isRpoActiveNotifSent><externalId xsi:nil="true"/></offerInstanceList><orderIdentifier><attribs>0</attribs><orderId changed="true" set="true"><value>28589182043</value></orderId><orderNumber changed="true" set="true"><value>28589182043</value></orderNumber><inforLeadId xsi:nil="true"/></orderIdentifier><serviceOrderId><attribs>0</attribs><serviceOrderId changed="true" set="true"><value>29440592043</value></serviceOrderId><orderId changed="true" set="true"><value>28589182043</value></orderId></serviceOrderId></output></q0:output></q0:SubscriberAddOfferInstanceResponse></soapenv:Body></soapenv:Envelope>